Metadata-Version: 2.1
Name: chimige-api
Version: 1.0
Summary: Api для соцсети Chimige (Чимиге)
Home-page: UNKNOWN
Author-email: ma_mush@mail.ru
License: UNKNOWN
Platform: UNKNOWN
Requires-Python: >=3.6
